{
  "header": {
    "exhibit": "Utställning",
    "gallery": "Galleri",
    "about": "Om",
    "contact": "Kontakt"
  },
  "landing": {
    "pageTitle": "Konst[galleri] | Kajsa Unge",
    "title": "Galleri",
    "titleDesc": "Originalmålningar"
  },
  "exhibition": {
    "pageTitle": "Utställningar[konst] | Kajsa Unge",
    "title": "Utställningar",
    "titleDesc": "Pågående & Kommande",
    "titlePrev": "Tidigare",
    "titleDescPrev": "Utställningar",
    "exhibitionDetails": {
      "open": "Öppet",
      "aw": "AW",
      "vernissage": "Vernissage",
      "finnisage": "Finnisage",
      "place": "Plats",
      "gallery": "Mer info"
    },
    "exhibitions": {
      "kvinna": {
        "title": "Grupputställning - Mars 2026",
        "aw": "TBA",
        "vernissage": "Internationella kvinnodagen 2026",
        "finnisage": "TBA",
        "place": "Galleri86Stockholm, Skånegatan 86, Stockholm",
        "desc": "Tillsammans med gallerist Erika Wilhelmsson arrangerar jag en hejdundrande hyllning till internationella kvinnodagen 2026. Det är långt dit men in me't i kalendern så ses vi då!"
      },
      "clarion": {
        "title": "Solo exhibition - Juni-September 2024",
        "vernissage": "14:e Juni kl 17",
        "address": "Ringvägen 98, Stockholm",
        "open": "Juni till slutet av september",
        "place": "Clarion Hotel Stockholm, Ringvägen 98, Stockholm",
        "placeUrl": "https://linktr.ee/clarionstockholm",
        "url": "https://fb.me/e/1sRK8fRzi",
        "urlText": "Eventsida",
        "desc": "I sommar möts du av min konst när du kliver in i lobbyn på ett av Stockholms snyggaste och mest genuina hotell. Utställningens ämne kan ge associationer till ytlighet, skönhet och yta, medan fokus i själva verket ligger på det inre skiftet, den efterlängtade och nödvändiga förändringen. Kom och träffa mig, njut av lättare tilltugg och dryck och upplev en inspirerande kväll med konst och kreativitet den 14 juni. Vi ses där!"
      }
    }
  },
  "about": {
    "pageTitle": "Om[konst] | Kajsa Unge",
    "title": "Om konstnären",
    "titleDesc": "Kajsa Unge",
    "intro1": "Kajsa Unge (f. 1982) är uppvuxen på Gotland och är idag bosatt och verksam i Stockholm. Hennes konstnärliga arbete utforskar styrkan i det sårbara – där ytan sällan fullt ut berättar historien.",
    "quote": "'Skapandeprocessen är intuitiv och organiskt formad, vilket ger verken en rå men samtidigt poetisk närvaro.'",
    "intro2": "Vid sidan av sitt konstnärskap är hon verksam som digital designer och webbutvecklare med fokus på kreativa och interaktiva lösningar.",
    "intro3": "Sidan växer i takt med skapandet där mer info och konst läggs till allteftersom. Hör gärna av dig till",
    "intro4": "med förfrågningar.",
    "insta": "📸 Följ för process, tankar, inspiration etc",
    "instaUrl": "https://www.instagram.com/konst.kajsaunge/",
    "facts": "Korta fakta",
    "fact": {
      "origin": "Autodidakt fram till 2023, då hon gick konstprogrammet vid Ågesta folkhögskola",
      "drive": "Inspirerad av naturen, särskilt vatten",
      "education": "Kandidatexamen i Grafisk design från Berghs och Billy Blue School of Graphic art",
      "current": "Fördjupat intresse i hälsa, sälskillt korrelationen mellan kropp och sinne",
      "portfolio": "Se portfolio",
      "portfolioUrl": "https://kajsaunge.se/cv"
    }
  },
  "contact": {
    "pageTitle": "Kontakt[beställning] | Kajsa Unge",
    "title": "Kontakt",
    "titleDesc": "Förfrågning och beställning",
    "intro": "Har du några som helst frågor kring konsten, ett potentiellt samarbete eller bara vill snacka lite når du mig enklast på",
    "intro2": ". Du kan även använda formuläret här på sidan.",
    "order": "Beställning",
    "orderDesc1": "För beställning fyller du i formuläret eller skickar ett mail till",
    "orderDesc2": "Skriv gärna i meddelandet hur du vill få din tavla levererad. Befinner du dig i Stockholmsområdet kan vi mötas för överlämning och det går även utmärkt att skicka tavlan, då tillkommer frakt.",
    "form": {
      "name": "Namn",
      "namePlaceholder": "Ditt namn",
      "mail": "E-post",
      "mailPlaceholder": "Din e-post",
      "message": "Meddelande",
      "messagePlaceholder": "Ditt meddelande",
      "submit": "Skicka",
      "successMsg": "Yey! Du får återkoppling inom kort :)"
    }
  },
  "slug": {
    "breadcrumb": "Till galleriet",
    "prev": "Föregående",
    "next": "Nästa",
    "pageTitle": "Konstverk:",
    "title": "Originalmålning:",
    "titleDesc": "Konst för unika rum",
    "detailsTitle": "Detaljer",
    "year": "Årtal",
    "price": "Pris",
    "size": "Storlek",
    "material": "Material",
    "frame": "Ram",
    "requestFrame": "Tillgänglig vid förfrågan",
    "delivery": "Leverans",
    "order": "Beställning",
    "pickup": "Skickas globalt eller upphämtning i Stockholmsområdet",
    "order1": "För beställning fyller du i formuläret eller skickar ett mail till",
    "order2": "Skriv gärna i meddelandet hur du vill få din tavla levererad. Befinner du dig i Stockholmsområdet kan vi mötas för överlämning och det går även utmärkt att skicka tavlan, då tillkommer frakt."
  },
  "card": {
    "size": "Storlek:",
    "price": "Pris:",
    "status": "",
    "frame": " (ram ingår)",
    "new": "Ny",
    "reserved": "Bokad",
    "sold": "Såld"
  },
  "general": {
    "more": "Se fler",
    "gallery": "Galleri",
    "galleryDesc": "Originalmålningar",
    "priceUnit": "kr",
    "sizeUnit": "cm",
    "on": "på"
  }
}
